wikiquote/__init__.py
wikiquote/constants.py
wikiquote/qotd.py
wikiquote/quotes.py
wikiquote/utils.py
wikiquote/langs/__init__.py
wikiquote/langs/de.py
wikiquote/langs/en.py
wikiquote/langs/es.py
wikiquote/langs/eu.py
wikiquote/langs/fr.py
wikiquote/langs/he.py
wikiquote/langs/it.py
wikiquote/langs/pl.py
wikiquote/langs/pt.py
wikiquote-0.1.18.dist-info/METADATA
wikiquote-0.1.18.dist-info/WHEEL
wikiquote-0.1.18.dist-info/licenses/LICENSE
wikiquote-0.1.18.dist-info/RECORD
