Metadata-Version: 2.4
Name: wikiquote
Version: 0.1.18
Summary: Retrieve quotes from any Wikiquote article.
Project-URL: Homepage, https://github.com/federicotdn/wikiquote
Project-URL: Repository, https://github.com/federicotdn/wikiquote
Author-email: Federico Tedin <federicotedin@gmail.com>
License-Expression: MIT
License-File: LICENSE
Keywords: api,day,python,qotd,quote,quotes,wikiquote
Classifier: License :: OSI Approved :: MIT License
Classifier: Programming Language :: Python :: 3 :: Only
Classifier: Topic :: Utilities
Requires-Python: <4,>=3.9
Requires-Dist: lxml~=5.4
